rtg/__init__.py
rtg/__main__.py
rtg/decode.py
rtg/decode_pro.py
rtg/exp.py
rtg/export.py
rtg/fork.py
rtg/pipeline.py
rtg/prep.py
rtg/registry.py
rtg/schema.py
rtg/train.py
rtg/transform.py
rtg/utils.py
rtg/big/__init__.py
rtg/big/exp.py
rtg/big/postgres.py
rtg/data/__init__.py
rtg/data/codec.py
rtg/data/dataset.py
rtg/data/dummy.py
rtg/distrib/__init__.py
rtg/distrib/launch.py
rtg/emb/__init__.py
rtg/emb/tfmcls.py
rtg/emb/word2vec.py
rtg/eval/__init__.py
rtg/eval/clsmetric.py
rtg/eval/datastat.py
rtg/eval/freq_bias.py
rtg/eval/imbalance.py
rtg/eval/linebleu.py
rtg/eval/nist_bleu.py
rtg/eval/perplexity.py
rtg/lm/__init__.py
rtg/lm/rnnlm.py
rtg/lm/tfmlm.py
rtg/module/__init__.py
rtg/module/criterion.py
rtg/module/decoder.py
rtg/module/generator.py
rtg/module/hybridmt.py
rtg/module/mtfmnmt.py
rtg/module/rnnmt.py
rtg/module/schedule.py
rtg/module/skptfmnmt.py
rtg/module/subcls_tfmnmt.py
rtg/module/tfmnmt.py
rtg/module/trainer.py
rtg/module/wvskptfmnmt.py
rtg/module/wvtfmnmt.py
rtg/module/ext/__init__.py
rtg/module/ext/robertamt.py
rtg/module/ext/tfmextemb.py
rtg/serve/__init__.py
rtg/serve/__main__.py
rtg/serve/app.py
rtg/serve/static/docs.html
rtg/serve/static/css/bootstrap.min.css
rtg/serve/static/css/highlight-default.css
rtg/serve/static/favicon/android-chrome-192x192.png
rtg/serve/static/favicon/android-chrome-512x512.png
rtg/serve/static/favicon/apple-touch-icon.png
rtg/serve/static/favicon/favicon-16x16.png
rtg/serve/static/favicon/favicon-32x32.png
rtg/serve/static/favicon/favicon.ico
rtg/serve/static/js/bootstrap.bundle.min.js
rtg/serve/static/js/highlight.pack.js
rtg/serve/static/js/jquery-3.5.1.min.js
rtg/serve/static/js/plotly-2.6.3.min.js
rtg/serve/templates/about.html
rtg/serve/templates/base.html
rtg/serve/templates/conf.yml.html
rtg/serve/templates/home.html
rtg/serve/templates/index.html
rtg/serve/templates/visual.html
rtg/syscomb/__init__.py
rtg/syscomb/__main__.py
rtg/syscomb/combo.py
rtg/tool/__init__.py
rtg/tool/attn_bleed.py
rtg/tool/augment.py
rtg-0.7.2.dist-info/LICENSE
rtg-0.7.2.dist-info/METADATA
rtg-0.7.2.dist-info/WHEEL
rtg-0.7.2.dist-info/entry_points.txt
rtg-0.7.2.dist-info/top_level.txt
rtg-0.7.2.dist-info/RECORD
