Metadata-Version: 2.1
Name: rtg
Version: 0.7.2
Summary: Reader Translator Generator(RTG), a Neural Machine Translator(NMT) toolkit based on Pytorch
Home-page: https://isi-nlp.github.io/rtg/
Author: Thamme Gowda
Author-email: tg@isi.edu
License: UNKNOWN
Platform: any
Classifier: Programming Language :: Python :: 3.7
Classifier: License :: OSI Approved :: Apache Software License
Classifier: Operating System :: OS Independent
Classifier: Intended Audience :: Science/Research
Classifier: Topic :: Scientific/Engineering :: Artificial Intelligence
Requires-Python: >=3.7
Requires-Dist: ruamel.yaml (>=0.17.10)
Requires-Dist: sacrebleu-macrof (==2.0.1)
Requires-Dist: sentencepiece (>=0.1.85)
Requires-Dist: tensorboard (>=2.6.0)
Requires-Dist: tqdm (>=4.45.0)
Requires-Dist: nlcodec (>=0.5)
Requires-Dist: torch (>=1.10)
Requires-Dist: sacremoses (>=0.0.45)
Requires-Dist: portalocker (>=2.0.0)
Requires-Dist: torchtext (>=0.10.0)
Requires-Dist: pyspark (>=3.0.0)
